README
setup.py
bettercache/__init__.py
bettercache/decorators.py
bettercache/handlers.py
bettercache/middleware.py
bettercache/models.py
bettercache/objects.py
bettercache/proxy.py
bettercache/settings.py
bettercache/tasks.py
bettercache/testing.py
bettercache/urls.py
bettercache/utils.py
bettercache/views.py
bettercache.egg-info/PKG-INFO
bettercache.egg-info/SOURCES.txt
bettercache.egg-info/dependency_links.txt
bettercache.egg-info/requires.txt
bettercache.egg-info/top_level.txt
bettercache/templatetags/__init__.py
bettercache/templatetags/bettercache.py
bettercache/tests/__init__.py
bettercache/tests/settings.py
bettercache/tests/test_decorators.py
bettercache/tests/test_middleware.py
bettercache/tests/test_objects.py
bettercache/tests/test_proxy.py
bettercache/tests/test_tasks.py
bettercache/tests/test_testing.py
bettercache/tests/test_utils.py
bettercache/tests/test_views.py
bettercachedemo/__init__.py
bettercachedemo/manage.py
bettercachedemo/settings.py
bettercachedemo/urls.py
bettercachedemo/views.py
docs/__init__.py
docs/conf.py
docs/settings.py