Metadata-Version: 1.1
Name: bettercache
Version: 0.7
Summary: A suite of better cache tools for Django.
Home-page: http://github.com/ironfroggy/django-better-cache
Author: Calvin Spealman, Cox Media Group
Author-email: ironfroggy@gmail.com, opensource@coxinc.com
License: MIT
Platform: UNKNOWN
Classifier: Programming Language :: Python :: 2
Classifier: Programming Language :: Python :: 3
